easy_tfrecords/__init__.py
easy_tfrecords/easy_tfrecords.py
easy_tfrecords-0.1.0.dist-info/METADATA
easy_tfrecords-0.1.0.dist-info/WHEEL
easy_tfrecords-0.1.0.dist-info/top_level.txt
easy_tfrecords-0.1.0.dist-info/RECORD
