Metadata-Version: 2.1
Name: easy-tfrecords
Version: 0.1.0
Summary: Package to streamline reading and writing data to tfrecord files
Home-page: https://github.com/pckosek/easy_tfrecords
Author: Paul Kosek
Author-email: pckosek@fcps.edu
License: UNKNOWN
Keywords: tensorflow tensor machine learning tfrecord
Platform: UNKNOWN
Classifier: Programming Language :: Python :: 3
Classifier: License :: OSI Approved :: MIT License
Classifier: Operating System :: OS Independent
